{
  "meta": {
    "timestamp": "2026-07-13 11:20:49 ET",
    "market_open": true,
    "watchlist": [
      "AMD",
      "NVDA",
      "INTC",
      "RY",
      "BNS",
      "TU",
      "AC"
    ],
    "bars_count": {
      "AMD": 96,
      "NVDA": 96,
      "INTC": 96,
      "RY": 96,
      "BNS": 96,
      "TU": 96,
      "AC": 0
    }
  },
  "symbols": {
    "AMD": {
      "price": {
        "last": 548.15,
        "bid": 547.92,
        "ask": 548.38,
        "spread": 0.46,
        "chg_pct": -1.75,
        "volume": 8694385,
        "session_high": 548.66,
        "session_low": 526.92,
        "session_mid": 537.79
      },
      "vwap": {
        "vwap": 537.32,
        "upper": 549.51,
        "lower": 525.13,
        "slope": 0.0325,
        "vs_vwap": 10.83,
        "above_vwap": true
      },
      "indicators": {
        "rsi": 64.2,
        "macd_hist": 0.3273,
        "macd_sig": 0.7643,
        "macd_dir": "BULLISH",
        "bb_upper": 548.91,
        "bb_lower": 541.69,
        "bb_pct_b": 0.875,
        "bb_state": "SQUEEZE",
        "atr": 1.3643,
        "rvol": 1.0
      },
      "obv": {
        "obv_millions": 0.001,
        "delta_1min": -0.0,
        "delta_5min": -0.0,
        "divergence": "CONFIRMED",
        "trend": "\u2192"
      },
      "candles": {
        "single": "\ud83d\udd34_CANDLE",
        "multi": "N/A",
        "last3": [
          {
            "t": "11:03",
            "color": "\ud83d\udfe2",
            "o": 547.5,
            "h": 548.28,
            "l": 547.36,
            "c": 548.14
          },
          {
            "t": "11:04",
            "color": "\ud83d\udd34",
            "o": 548.14,
            "h": 548.64,
            "l": 547.66,
            "c": 548.03
          },
          {
            "t": "11:05",
            "color": "\ud83d\udd34",
            "o": 548.1,
            "h": 548.46,
            "l": 547.93,
            "c": 548.01
          }
        ]
      },
      "options": {
        "expiry": "2026-07-13",
        "spot": 547.37,
        "max_pain": 545.0,
        "call_wall": 590.0,
        "call_wall_oi": 3144.0,
        "put_wall": 515.0,
        "put_wall_oi": 2638.0,
        "gamma_flip": 502.5,
        "pc_ratio": 1.19,
        "atm_iv": 81.1,
        "imbalance_pct": -15.5,
        "imbalance_bias": "PUT_HEAVY -16%",
        "top_calls": [
          {
            "strike": 557.5,
            "oi": 1879.0,
            "vol": 686.0
          },
          {
            "strike": 560.0,
            "oi": 538.0,
            "vol": 2926.0
          },
          {
            "strike": 555.0,
            "oi": 532.0,
            "vol": 1612.0
          },
          {
            "strike": 550.0,
            "oi": 445.0,
            "vol": 5241.0
          },
          {
            "strike": 552.5,
            "oi": 379.0,
            "vol": 913.0
          }
        ],
        "top_puts": [
          {
            "strike": 545.0,
            "oi": 2317.0,
            "vol": 2258.0
          },
          {
            "strike": 537.5,
            "oi": 767.0,
            "vol": 755.0
          },
          {
            "strike": 550.0,
            "oi": 717.0,
            "vol": 294.0
          },
          {
            "strike": 542.5,
            "oi": 583.0,
            "vol": 478.0
          },
          {
            "strike": 547.5,
            "oi": 427.0,
            "vol": 1952.0
          }
        ],
        "total_call_oi": 17185.0,
        "total_put_oi": 20479.0,
        "error": null
      },
      "algo": {
        "score": 4,
        "checks": {
          "vwap": "BUY_BIAS",
          "rsi": "NEUTRAL",
          "macd": "BULLISH",
          "obv": "CONFIRMED",
          "options": "PUT_HEAVY_CEILING",
          "nq": "FLAT",
          "sector": "N/A",
          "bb": "MID_RANGE"
        },
        "direction": "NEUTRAL",
        "setup": null
      },
      "sentiment": {
        "adanos": {
          "symbol": "AMD",
          "signal": "Buy",
          "conviction": 91,
          "reddit": 26,
          "news": 74
        },
        "apewisdom": {
          "symbol": "AMD",
          "mentions": 24,
          "bullish_pct": 43,
          "bearish_pct": 57
        },
        "short_interest": {
          "squeeze_risk": "LOW"
        }
      },
      "news": [],
      "updated_at": "2026-07-13 11:20:42 ET"
    },
    "NVDA": {
      "price": {
        "last": 207.29,
        "bid": 207.27,
        "ask": 207.3,
        "spread": 0.03,
        "chg_pct": -1.74,
        "volume": 35324216,
        "session_high": 210.57,
        "session_low": 206.64,
        "session_mid": 208.6
      },
      "vwap": {
        "vwap": 208.48,
        "upper": 210.11,
        "lower": 206.85,
        "slope": -0.0039,
        "vs_vwap": -1.19,
        "above_vwap": false
      },
      "indicators": {
        "rsi": 45.8,
        "macd_hist": 0.0573,
        "macd_sig": -0.1755,
        "macd_dir": "BULLISH",
        "bb_upper": 207.72,
        "bb_lower": 206.93,
        "bb_pct_b": 0.532,
        "bb_state": "SQUEEZE",
        "atr": 0.3036,
        "rvol": 1.0
      },
      "obv": {
        "obv_millions": -0.007,
        "delta_1min": 0.001,
        "delta_5min": 0.001,
        "divergence": "BULLISH_DIV",
        "trend": "\u25b2"
      },
      "candles": {
        "single": "\ud83d\udfe2_CANDLE",
        "multi": "N/A",
        "last3": [
          {
            "t": "11:03",
            "color": "\ud83d\udd34",
            "o": 207.52,
            "h": 207.56,
            "l": 207.3,
            "c": 207.46
          },
          {
            "t": "11:04",
            "color": "\ud83d\udd34",
            "o": 207.47,
            "h": 207.52,
            "l": 207.2,
            "c": 207.29
          },
          {
            "t": "11:05",
            "color": "\ud83d\udfe2",
            "o": 207.29,
            "h": 207.36,
            "l": 207.24,
            "c": 207.35
          }
        ]
      },
      "options": {
        "expiry": "2026-07-13",
        "spot": 207.53,
        "max_pain": 202.5,
        "call_wall": 212.5,
        "call_wall_oi": 15097.0,
        "put_wall": 175.0,
        "put_wall_oi": 12207.0,
        "gamma_flip": 197.5,
        "pc_ratio": 0.96,
        "atm_iv": 41.8,
        "imbalance_pct": 32.7,
        "imbalance_bias": "CALL_HEAVY +33%",
        "top_calls": [
          {
            "strike": 212.5,
            "oi": 15097.0,
            "vol": 90797.0
          },
          {
            "strike": 210.0,
            "oi": 12732.0,
            "vol": 179546.0
          },
          {
            "strike": 215.0,
            "oi": 12566.0,
            "vol": 58608.0
          },
          {
            "strike": 205.0,
            "oi": 11318.0,
            "vol": 6409.0
          },
          {
            "strike": 200.0,
            "oi": 8620.0,
            "vol": 713.0
          }
        ],
        "top_puts": [
          {
            "strike": 205.0,
            "oi": 9030.0,
            "vol": 82053.0
          },
          {
            "strike": 200.0,
            "oi": 8498.0,
            "vol": 8770.0
          },
          {
            "strike": 192.5,
            "oi": 6018.0,
            "vol": 2511.0
          },
          {
            "strike": 190.0,
            "oi": 5463.0,
            "vol": 1196.0
          },
          {
            "strike": 207.5,
            "oi": 4299.0,
            "vol": 85466.0
          }
        ],
        "total_call_oi": 107173.0,
        "total_put_oi": 103408.0,
        "error": null
      },
      "algo": {
        "score": 4,
        "checks": {
          "vwap": "SELL_BIAS",
          "rsi": "NEUTRAL",
          "macd": "BULLISH",
          "obv": "BULLISH_DIV",
          "options": "CALL_HEAVY_FLOOR",
          "nq": "FLAT",
          "sector": "N/A",
          "bb": "MID_RANGE"
        },
        "direction": "LONG",
        "setup": null
      },
      "sentiment": {
        "adanos": {
          "symbol": "NVDA",
          "signal": "Buy",
          "conviction": 70,
          "reddit": 29,
          "news": 82
        },
        "apewisdom": {
          "symbol": "NVDA",
          "mentions": 48,
          "bullish_pct": 80,
          "bearish_pct": 20
        },
        "short_interest": {
          "squeeze_risk": "LOW"
        }
      },
      "news": [],
      "updated_at": "2026-07-13 11:20:44 ET"
    },
    "INTC": {
      "price": {
        "last": 105.12,
        "bid": 105.08,
        "ask": 105.12,
        "spread": 0.04,
        "chg_pct": -4.3,
        "volume": 32304684,
        "session_high": 106.17,
        "session_low": 103.37,
        "session_mid": 104.77
      },
      "vwap": {
        "vwap": 104.87,
        "upper": 105.83,
        "lower": 103.91,
        "slope": 0.0011,
        "vs_vwap": 0.25,
        "above_vwap": true
      },
      "indicators": {
        "rsi": 48.0,
        "macd_hist": 0.0172,
        "macd_sig": -0.0318,
        "macd_dir": "BULLISH",
        "bb_upper": 105.7,
        "bb_lower": 104.53,
        "bb_pct_b": 0.479,
        "bb_state": "SQUEEZE",
        "atr": 0.2936,
        "rvol": 1.0
      },
      "obv": {
        "obv_millions": 0.01,
        "delta_1min": -0.0,
        "delta_5min": -0.003,
        "divergence": "CONFIRMED",
        "trend": "\u2192"
      },
      "candles": {
        "single": "\ud83d\udd34_CANDLE",
        "multi": "THREE_RED",
        "last3": [
          {
            "t": "11:03",
            "color": "\ud83d\udd34",
            "o": 105.24,
            "h": 105.31,
            "l": 105.06,
            "c": 105.11
          },
          {
            "t": "11:04",
            "color": "\ud83d\udd34",
            "o": 105.13,
            "h": 105.29,
            "l": 105.06,
            "c": 105.12
          },
          {
            "t": "11:05",
            "color": "\ud83d\udd34",
            "o": 105.1,
            "h": 105.18,
            "l": 105.07,
            "c": 105.09
          }
        ]
      },
      "options": {
        "expiry": "2026-07-13",
        "spot": 105.64,
        "max_pain": 110.0,
        "call_wall": 120.0,
        "call_wall_oi": 3451.0,
        "put_wall": 100.0,
        "put_wall_oi": 6147.0,
        "gamma_flip": 109.0,
        "pc_ratio": 0.79,
        "atm_iv": 78.2,
        "imbalance_pct": -1.0,
        "imbalance_bias": "BALANCED (-1%)",
        "top_calls": [
          {
            "strike": 120.0,
            "oi": 3451.0,
            "vol": 253.0
          },
          {
            "strike": 110.0,
            "oi": 2513.0,
            "vol": 3523.0
          },
          {
            "strike": 125.0,
            "oi": 2309.0,
            "vol": 192.0
          },
          {
            "strike": 113.0,
            "oi": 1818.0,
            "vol": 722.0
          },
          {
            "strike": 115.0,
            "oi": 1672.0,
            "vol": 536.0
          }
        ],
        "top_puts": [
          {
            "strike": 100.0,
            "oi": 6147.0,
            "vol": 1986.0
          },
          {
            "strike": 110.0,
            "oi": 1293.0,
            "vol": 102.0
          },
          {
            "strike": 105.0,
            "oi": 1093.0,
            "vol": 7779.0
          },
          {
            "strike": 88.0,
            "oi": 1036.0,
            "vol": 180.0
          },
          {
            "strike": 97.0,
            "oi": 952.0,
            "vol": 626.0
          }
        ],
        "total_call_oi": 24536.0,
        "total_put_oi": 19329.0,
        "error": null
      },
      "algo": {
        "score": 3,
        "checks": {
          "vwap": "BUY_BIAS",
          "rsi": "NEUTRAL",
          "macd": "BULLISH",
          "obv": "CONFIRMED",
          "options": "NEUTRAL",
          "nq": "FLAT",
          "sector": "N/A",
          "bb": "MID_RANGE"
        },
        "direction": "LONG",
        "setup": null
      },
      "sentiment": {
        "adanos": {
          "symbol": "INTC",
          "signal": "Buy",
          "conviction": 59,
          "reddit": 29,
          "news": 68
        },
        "apewisdom": {
          "symbol": "INTC",
          "mentions": 14,
          "bullish_pct": 56,
          "bearish_pct": 44
        },
        "short_interest": {
          "squeeze_risk": "LOW"
        }
      },
      "news": [],
      "updated_at": "2026-07-13 11:20:45 ET"
    },
    "RY": {
      "price": {
        "last": 210.17,
        "bid": 210.21,
        "ask": 210.29,
        "spread": 0.08,
        "chg_pct": -0.44,
        "volume": 249810,
        "session_high": 212.36,
        "session_low": 210.03,
        "session_mid": 211.19
      },
      "vwap": {
        "vwap": 211.37,
        "upper": 212.41,
        "lower": 210.33,
        "slope": -0.0137,
        "vs_vwap": -1.2,
        "above_vwap": false
      },
      "indicators": {
        "rsi": 33.0,
        "macd_hist": -0.023,
        "macd_sig": -0.2276,
        "macd_dir": "BEARISH",
        "bb_upper": 211.19,
        "bb_lower": 209.97,
        "bb_pct_b": 0.213,
        "bb_state": "SQUEEZE",
        "atr": 0.1264,
        "rvol": 1.0
      },
      "obv": {
        "obv_millions": -0.0,
        "delta_1min": -0.0,
        "delta_5min": 0.0,
        "divergence": "CONFIRMED",
        "trend": "\u2192"
      },
      "candles": {
        "single": "MARUBOZU_\ud83d\udd34",
        "multi": "THREE_RED",
        "last3": [
          {
            "t": "11:03",
            "color": "\ud83d\udd34",
            "o": 210.27,
            "h": 210.31,
            "l": 210.14,
            "c": 210.23
          },
          {
            "t": "11:04",
            "color": "\ud83d\udd34",
            "o": 210.29,
            "h": 210.35,
            "l": 210.23,
            "c": 210.27
          },
          {
            "t": "11:05",
            "color": "\ud83d\udd34",
            "o": 210.27,
            "h": 210.27,
            "l": 210.23,
            "c": 210.23
          }
        ]
      },
      "options": {
        "expiry": "2026-07-17",
        "spot": 210.08,
        "max_pain": 180.0,
        "call_wall": 210.0,
        "call_wall_oi": 2470.0,
        "put_wall": 185.0,
        "put_wall_oi": 614.0,
        "gamma_flip": 175.0,
        "pc_ratio": 0.62,
        "atm_iv": 15.6,
        "imbalance_pct": 65.8,
        "imbalance_bias": "CALL_HEAVY +66%",
        "top_calls": [
          {
            "strike": 210.0,
            "oi": 2470.0,
            "vol": 7.0
          },
          {
            "strike": 195.0,
            "oi": 158.0,
            "vol": 0
          },
          {
            "strike": 200.0,
            "oi": 122.0,
            "vol": 2.0
          },
          {
            "strike": 220.0,
            "oi": 98.0,
            "vol": 0
          }
        ],
        "top_puts": [
          {
            "strike": 210.0,
            "oi": 266.0,
            "vol": 24.0
          },
          {
            "strike": 200.0,
            "oi": 184.0,
            "vol": 14.0
          },
          {
            "strike": 195.0,
            "oi": 138.0,
            "vol": 5.0
          },
          {
            "strike": 220.0,
            "oi": 0,
            "vol": 0
          }
        ],
        "total_call_oi": 5500.0,
        "total_put_oi": 3413.0,
        "error": null
      },
      "algo": {
        "score": 5,
        "checks": {
          "vwap": "SELL_BIAS",
          "rsi": "NEUTRAL",
          "macd": "BEARISH",
          "obv": "CONFIRMED",
          "options": "MAX_PAIN_GRAVITY_$180.0",
          "nq": "FLAT",
          "sector": "N/A",
          "bb": "LOWER_BAND"
        },
        "direction": "SHORT",
        "setup": {
          "direction": "SHORT",
          "entry": 210.17,
          "stop": 210.26,
          "target": 209.98,
          "rr": 2.0,
          "reason": "vwap:SELL_BIAS | macd:BEARISH"
        }
      },
      "sentiment": {
        "adanos": {
          "symbol": "RY",
          "signal": "Buy",
          "conviction": 93,
          "news": 0
        },
        "apewisdom": {
          "symbol": "RY",
          "mentions": 0
        },
        "short_interest": {
          "squeeze_risk": "LOW"
        }
      },
      "news": [],
      "updated_at": "2026-07-13 11:20:46 ET"
    },
    "BNS": {
      "price": {
        "last": 87.43,
        "bid": 87.41,
        "ask": 87.46,
        "spread": 0.05,
        "chg_pct": -0.18,
        "volume": 311136,
        "session_high": 88.17,
        "session_low": 87.38,
        "session_mid": 87.78
      },
      "vwap": {
        "vwap": 87.81,
        "upper": 88.13,
        "lower": 87.49,
        "slope": -0.0025,
        "vs_vwap": -0.38,
        "above_vwap": false
      },
      "indicators": {
        "rsi": 30.1,
        "macd_hist": -0.0129,
        "macd_sig": -0.0987,
        "macd_dir": "BEARISH",
        "bb_upper": 87.9,
        "bb_lower": 87.32,
        "bb_pct_b": 0.19,
        "bb_state": "SQUEEZE",
        "atr": 0.0564,
        "rvol": 1.0
      },
      "obv": {
        "obv_millions": -0.0,
        "delta_1min": -0.0,
        "delta_5min": -0.0,
        "divergence": "CONFIRMED",
        "trend": "\u2192"
      },
      "candles": {
        "single": "MARUBOZU_\ud83d\udd34",
        "multi": "THREE_RED",
        "last3": [
          {
            "t": "11:03",
            "color": "\ud83d\udd34",
            "o": 87.46,
            "h": 87.46,
            "l": 87.41,
            "c": 87.44
          },
          {
            "t": "11:04",
            "color": "\ud83d\udd34",
            "o": 87.47,
            "h": 87.47,
            "l": 87.45,
            "c": 87.45
          },
          {
            "t": "11:05",
            "color": "\ud83d\udd34",
            "o": 87.44,
            "h": 87.44,
            "l": 87.43,
            "c": 87.43
          }
        ]
      },
      "options": {
        "expiry": "2026-07-17",
        "spot": 87.4,
        "max_pain": 87.5,
        "call_wall": 87.5,
        "call_wall_oi": 639.0,
        "put_wall": 77.5,
        "put_wall_oi": 300.0,
        "gamma_flip": 87.5,
        "pc_ratio": 0.72,
        "atm_iv": 15.4,
        "imbalance_pct": 16.8,
        "imbalance_bias": "CALL_HEAVY +17%",
        "top_calls": [
          {
            "strike": 87.5,
            "oi": 639.0,
            "vol": 0
          },
          {
            "strike": 90.0,
            "oi": 151.0,
            "vol": 0
          },
          {
            "strike": 95.0,
            "oi": 73.0,
            "vol": 0
          },
          {
            "strike": 85.0,
            "oi": 44.0,
            "vol": 25.0
          },
          {
            "strike": 80.0,
            "oi": 20.0,
            "vol": 0
          }
        ],
        "top_puts": [
          {
            "strike": 77.5,
            "oi": 300.0,
            "vol": 0
          },
          {
            "strike": 85.0,
            "oi": 137.0,
            "vol": 0
          },
          {
            "strike": 82.5,
            "oi": 61.0,
            "vol": 0
          },
          {
            "strike": 90.0,
            "oi": 48.0,
            "vol": 0
          },
          {
            "strike": 75.0,
            "oi": 42.0,
            "vol": 0
          }
        ],
        "total_call_oi": 930.0,
        "total_put_oi": 670.0,
        "error": null
      },
      "algo": {
        "score": 5,
        "checks": {
          "vwap": "SELL_BIAS",
          "rsi": "NEUTRAL",
          "macd": "BEARISH",
          "obv": "CONFIRMED",
          "options": "CALL_HEAVY_FLOOR",
          "nq": "FLAT",
          "sector": "N/A",
          "bb": "LOWER_BAND"
        },
        "direction": "SHORT",
        "setup": {
          "direction": "SHORT",
          "entry": 87.43,
          "stop": 87.47,
          "target": 87.35,
          "rr": 2.0,
          "reason": "vwap:SELL_BIAS | macd:BEARISH"
        }
      },
      "sentiment": {
        "adanos": null,
        "apewisdom": {
          "symbol": "BNS",
          "mentions": 0
        },
        "short_interest": {
          "squeeze_risk": "LOW"
        }
      },
      "news": [],
      "updated_at": "2026-07-13 11:20:48 ET"
    },
    "TU": {
      "price": {
        "last": 10.62,
        "bid": 10.62,
        "ask": 10.63,
        "spread": 0.01,
        "chg_pct": 1.92,
        "volume": 1937262,
        "session_high": 10.68,
        "session_low": 10.5,
        "session_mid": 10.59
      },
      "vwap": {
        "vwap": 10.61,
        "upper": 10.67,
        "lower": 10.55,
        "slope": 0.0001,
        "vs_vwap": 0.01,
        "above_vwap": true
      },
      "indicators": {
        "rsi": 47.8,
        "macd_hist": -0.005,
        "macd_sig": 0.0114,
        "macd_dir": "BEARISH",
        "bb_upper": 10.68,
        "bb_lower": 10.61,
        "bb_pct_b": 0.286,
        "bb_state": "SQUEEZE",
        "atr": 0.0107,
        "rvol": 1.0
      },
      "obv": {
        "obv_millions": 0.001,
        "delta_1min": 0.0,
        "delta_5min": -0.0,
        "divergence": "CONFIRMED",
        "trend": "\u2192"
      },
      "candles": {
        "single": "DOJI",
        "multi": "THREE_RED",
        "last3": [
          {
            "t": "11:03",
            "color": "\ud83d\udd34",
            "o": 10.64,
            "h": 10.64,
            "l": 10.63,
            "c": 10.63
          },
          {
            "t": "11:04",
            "color": "\ud83d\udfe2",
            "o": 10.63,
            "h": 10.64,
            "l": 10.63,
            "c": 10.63
          },
          {
            "t": "11:05",
            "color": "\ud83d\udfe2",
            "o": 10.63,
            "h": 10.63,
            "l": 10.63,
            "c": 10.63
          }
        ]
      },
      "options": {
        "expiry": "2026-07-17",
        "spot": 10.64,
        "max_pain": 10.0,
        "call_wall": 12.5,
        "call_wall_oi": 58.0,
        "put_wall": 10.0,
        "put_wall_oi": 329.0,
        "gamma_flip": 12.5,
        "pc_ratio": 2.72,
        "atm_iv": 37.2,
        "imbalance_pct": -46.2,
        "imbalance_bias": "PUT_HEAVY -46%",
        "top_calls": [
          {
            "strike": 12.5,
            "oi": 58.0,
            "vol": 0
          },
          {
            "strike": 10.0,
            "oi": 51.0,
            "vol": 3.0
          },
          {
            "strike": 15.0,
            "oi": 10.0,
            "vol": 0
          },
          {
            "strike": 17.5,
            "oi": 4.0,
            "vol": 0
          },
          {
            "strike": 2.5,
            "oi": 0,
            "vol": 0
          }
        ],
        "top_puts": [
          {
            "strike": 10.0,
            "oi": 329.0,
            "vol": 0
          },
          {
            "strike": 5.0,
            "oi": 5.0,
            "vol": 0
          },
          {
            "strike": 2.5,
            "oi": 0,
            "vol": 0
          },
          {
            "strike": 7.5,
            "oi": 0,
            "vol": 0
          },
          {
            "strike": 12.5,
            "oi": 0,
            "vol": 0
          }
        ],
        "total_call_oi": 123.0,
        "total_put_oi": 334.0,
        "error": null
      },
      "algo": {
        "score": 3,
        "checks": {
          "vwap": "NEUTRAL",
          "rsi": "NEUTRAL",
          "macd": "BEARISH",
          "obv": "CONFIRMED",
          "options": "PUT_HEAVY_CEILING",
          "nq": "FLAT",
          "sector": "N/A",
          "bb": "MID_RANGE"
        },
        "direction": "SHORT",
        "setup": null
      },
      "sentiment": {
        "adanos": {
          "symbol": "TU",
          "signal": "Buy",
          "conviction": 93,
          "reddit": 20,
          "news": 64
        },
        "apewisdom": {
          "symbol": "TU",
          "mentions": 1
        },
        "short_interest": {
          "squeeze_risk": "LOW"
        }
      },
      "news": [],
      "updated_at": "2026-07-13 11:20:49 ET"
    }
  },
  "futures": {
    "nq_price": 0,
    "nq_trend": "FLAT"
  },
  "sector": {
    "SOXX": {
      "price": 562.58,
      "chg_pct": -3.23
    },
    "SMH": {
      "price": 595.97,
      "chg_pct": -2.46
    },
    "QQQ": {
      "price": 717.72,
      "chg_pct": -1.07
    },
    "SPY": {
      "price": 752.31,
      "chg_pct": -0.35
    },
    "VIX": {
      "price": 16.23,
      "chg_pct": 7.98
    }
  },
  "macro": {
    "t10y2y": 0.35,
    "t10y2y_date": "#2026-07-10|",
    "t10y2y_regime": "risk-on",
    "cpi_nowcast_yoy": null,
    "cpi_nowcast_mom": null,
    "risk_on": false
  },
  "unusual_flow": [],
  "alerts": [
    {
      "time": "11:20",
      "symbol": "BNS",
      "type": "SHORT",
      "direction": "SHORT",
      "price": 87.43,
      "score": 5,
      "reason": "vwap:SELL_BIAS | macd:BEARISH"
    },
    {
      "time": "11:20",
      "symbol": "RY",
      "type": "SHORT",
      "direction": "SHORT",
      "price": 210.17,
      "score": 5,
      "reason": "vwap:SELL_BIAS | macd:BEARISH"
    },
    {
      "time": "11:19",
      "symbol": "BNS",
      "type": "SHORT",
      "direction": "SHORT",
      "price": 87.45,
      "score": 5,
      "reason": "vwap:SELL_BIAS | macd:BEARISH"
    },
    {
      "time": "11:19",
      "symbol": "RY",
      "type": "SHORT",
      "direction": "SHORT",
      "price": 210.26,
      "score": 5,
      "reason": "vwap:SELL_BIAS | macd:BEARISH"
    },
    {
      "time": "11:18",
      "symbol": "BNS",
      "type": "SHORT",
      "direction": "SHORT",
      "price": 87.47,
      "score": 5,
      "reason": "vwap:SELL_BIAS | macd:BEARISH"
    },
    {
      "time": "11:18",
      "symbol": "RY",
      "type": "SHORT",
      "direction": "SHORT",
      "price": 210.26,
      "score": 6,
      "reason": "vwap:SELL_BIAS | macd:BEARISH"
    },
    {
      "time": "11:17",
      "symbol": "RY",
      "type": "SHORT",
      "direction": "SHORT",
      "price": 210.08,
      "score": 6,
      "reason": "vwap:SELL_BIAS | macd:BEARISH"
    },
    {
      "time": "11:15",
      "symbol": "RY",
      "type": "SHORT",
      "direction": "SHORT",
      "price": 210.17,
      "score": 6,
      "reason": "vwap:SELL_BIAS | macd:BEARISH"
    },
    {
      "time": "11:14",
      "symbol": "TU",
      "type": "SHORT",
      "direction": "SHORT",
      "price": 10.65,
      "score": 5,
      "reason": ""
    },
    {
      "time": "11:14",
      "symbol": "RY",
      "type": "SHORT",
      "direction": "SHORT",
      "price": 210.4,
      "score": 5,
      "reason": "vwap:SELL_BIAS | macd:BEARISH"
    },
    {
      "time": "11:14",
      "symbol": "NVDA",
      "type": "LONG",
      "direction": "LONG",
      "price": 207.2,
      "score": 5,
      "reason": "macd:BULLISH"
    },
    {
      "time": "11:13",
      "symbol": "TU",
      "type": "SHORT",
      "direction": "SHORT",
      "price": 10.66,
      "score": 5,
      "reason": ""
    },
    {
      "time": "11:13",
      "symbol": "RY",
      "type": "SHORT",
      "direction": "SHORT",
      "price": 210.56,
      "score": 5,
      "reason": "vwap:SELL_BIAS | macd:BEARISH"
    },
    {
      "time": "11:12",
      "symbol": "TU",
      "type": "SHORT",
      "direction": "SHORT",
      "price": 10.65,
      "score": 5,
      "reason": ""
    },
    {
      "time": "11:12",
      "symbol": "BNS",
      "type": "SHORT",
      "direction": "SHORT",
      "price": 87.61,
      "score": 5,
      "reason": "vwap:SELL_BIAS | macd:BEARISH"
    },
    {
      "time": "11:12",
      "symbol": "RY",
      "type": "SHORT",
      "direction": "SHORT",
      "price": 210.66,
      "score": 5,
      "reason": "vwap:SELL_BIAS | macd:BEARISH"
    },
    {
      "time": "11:12",
      "symbol": "NVDA",
      "type": "LONG",
      "direction": "LONG",
      "price": 207.25,
      "score": 5,
      "reason": ""
    },
    {
      "time": "11:11",
      "symbol": "TU",
      "type": "SHORT",
      "direction": "SHORT",
      "price": 10.66,
      "score": 5,
      "reason": ""
    },
    {
      "time": "11:11",
      "symbol": "RY",
      "type": "SHORT",
      "direction": "SHORT",
      "price": 210.7,
      "score": 5,
      "reason": "vwap:SELL_BIAS | macd:BEARISH"
    },
    {
      "time": "11:10",
      "symbol": "NVDA",
      "type": "LONG",
      "direction": "LONG",
      "price": 206.9,
      "score": 5,
      "reason": ""
    },
    {
      "time": "11:09",
      "symbol": "TU",
      "type": "SHORT",
      "direction": "SHORT",
      "price": 10.65,
      "score": 5,
      "reason": ""
    },
    {
      "time": "11:09",
      "symbol": "BNS",
      "type": "SHORT",
      "direction": "SHORT",
      "price": 87.65,
      "score": 5,
      "reason": "vwap:SELL_BIAS | macd:BEARISH"
    },
    {
      "time": "11:09",
      "symbol": "RY",
      "type": "SHORT",
      "direction": "SHORT",
      "price": 210.81,
      "score": 5,
      "reason": "vwap:SELL_BIAS | macd:BEARISH"
    },
    {
      "time": "11:09",
      "symbol": "NVDA",
      "type": "LONG",
      "direction": "LONG",
      "price": 206.9,
      "score": 5,
      "reason": "macd:BULLISH"
    },
    {
      "time": "11:08",
      "symbol": "TU",
      "type": "SHORT",
      "direction": "SHORT",
      "price": 10.65,
      "score": 5,
      "reason": ""
    },
    {
      "time": "11:08",
      "symbol": "RY",
      "type": "SHORT",
      "direction": "SHORT",
      "price": 210.85,
      "score": 5,
      "reason": "vwap:SELL_BIAS | macd:BEARISH"
    },
    {
      "time": "11:08",
      "symbol": "NVDA",
      "type": "LONG",
      "direction": "LONG",
      "price": 207.25,
      "score": 5,
      "reason": "macd:BULLISH"
    },
    {
      "time": "11:07",
      "symbol": "TU",
      "type": "SHORT",
      "direction": "SHORT",
      "price": 10.65,
      "score": 5,
      "reason": ""
    },
    {
      "time": "11:07",
      "symbol": "RY",
      "type": "SHORT",
      "direction": "SHORT",
      "price": 210.98,
      "score": 5,
      "reason": "vwap:SELL_BIAS | macd:BEARISH"
    },
    {
      "time": "11:07",
      "symbol": "NVDA",
      "type": "LONG",
      "direction": "LONG",
      "price": 207.43,
      "score": 5,
      "reason": "macd:BULLISH"
    },
    {
      "time": "11:06",
      "symbol": "TU",
      "type": "SHORT",
      "direction": "SHORT",
      "price": 10.66,
      "score": 6,
      "reason": "rsi:OVERBOUGHT"
    },
    {
      "time": "11:06",
      "symbol": "RY",
      "type": "SHORT",
      "direction": "SHORT",
      "price": 210.9,
      "score": 5,
      "reason": "vwap:SELL_BIAS | macd:BEARISH"
    },
    {
      "time": "11:06",
      "symbol": "NVDA",
      "type": "LONG",
      "direction": "LONG",
      "price": 207.53,
      "score": 5,
      "reason": "macd:BULLISH_CROSS"
    },
    {
      "time": "11:04",
      "symbol": "RY",
      "type": "SHORT",
      "direction": "SHORT",
      "price": 210.96,
      "score": 5,
      "reason": "vwap:SELL_BIAS | macd:BEARISH"
    },
    {
      "time": "11:04",
      "symbol": "NVDA",
      "type": "SHORT",
      "direction": "SHORT",
      "price": 207.56,
      "score": 5,
      "reason": "vwap:SELL_BIAS | macd:BEARISH"
    },
    {
      "time": "11:03",
      "symbol": "TU",
      "type": "LONG",
      "direction": "LONG",
      "price": 10.64,
      "score": 5,
      "reason": "vwap:BUY_BIAS | macd:BULLISH"
    },
    {
      "time": "11:03",
      "symbol": "RY",
      "type": "SHORT",
      "direction": "SHORT",
      "price": 210.83,
      "score": 5,
      "reason": "vwap:SELL_BIAS | macd:BEARISH"
    },
    {
      "time": "11:03",
      "symbol": "NVDA",
      "type": "LONG",
      "direction": "LONG",
      "price": 207.36,
      "score": 5,
      "reason": ""
    },
    {
      "time": "11:02",
      "symbol": "TU",
      "type": "LONG",
      "direction": "LONG",
      "price": 10.62,
      "score": 5,
      "reason": "vwap:BUY_BIAS | macd:BULLISH"
    },
    {
      "time": "11:02",
      "symbol": "RY",
      "type": "SHORT",
      "direction": "SHORT",
      "price": 210.8,
      "score": 5,
      "reason": "vwap:SELL_BIAS | macd:BEARISH"
    },
    {
      "time": "11:02",
      "symbol": "NVDA",
      "type": "LONG",
      "direction": "LONG",
      "price": 207.09,
      "score": 5,
      "reason": ""
    },
    {
      "time": "11:01",
      "symbol": "RY",
      "type": "SHORT",
      "direction": "SHORT",
      "price": 211.01,
      "score": 5,
      "reason": "vwap:SELL_BIAS | macd:BEARISH"
    },
    {
      "time": "11:01",
      "symbol": "NVDA",
      "type": "SHORT",
      "direction": "SHORT",
      "price": 207.09,
      "score": 5,
      "reason": "vwap:SELL_BIAS | macd:BEARISH"
    },
    {
      "time": "11:00",
      "symbol": "RY",
      "type": "SHORT",
      "direction": "SHORT",
      "price": 211.01,
      "score": 5,
      "reason": "vwap:SELL_BIAS | macd:BEARISH"
    },
    {
      "time": "11:00",
      "symbol": "NVDA",
      "type": "LONG",
      "direction": "LONG",
      "price": 207.31,
      "score": 5,
      "reason": ""
    },
    {
      "time": "10:58",
      "symbol": "RY",
      "type": "SHORT",
      "direction": "SHORT",
      "price": 210.82,
      "score": 5,
      "reason": "vwap:SELL_BIAS | macd:BEARISH"
    },
    {
      "time": "10:58",
      "symbol": "NVDA",
      "type": "SHORT",
      "direction": "SHORT",
      "price": 207.12,
      "score": 5,
      "reason": "vwap:SELL_BIAS | macd:BEARISH"
    },
    {
      "time": "10:57",
      "symbol": "RY",
      "type": "SHORT",
      "direction": "SHORT",
      "price": 211.06,
      "score": 5,
      "reason": "vwap:SELL_BIAS | macd:BEARISH_CROSS"
    },
    {
      "time": "10:57",
      "symbol": "NVDA",
      "type": "SHORT",
      "direction": "SHORT",
      "price": 207.46,
      "score": 5,
      "reason": "vwap:SELL_BIAS | macd:BEARISH"
    },
    {
      "time": "10:56",
      "symbol": "NVDA",
      "type": "SHORT",
      "direction": "SHORT",
      "price": 207.76,
      "score": 5,
      "reason": "vwap:SELL_BIAS | macd:BEARISH"
    }
  ]
}